{"title":"Bikini-Pleasure.14.01.27.Gabrielle.Frolic.XXX.iMAGESET-YAPG","uid":9529613,"size":74166972,"categoryP":"porn","categoryS":"other","magnet":"?xt=urn:btih:0b8216e1edb7573a8f309e46683246b73a71fa38&amp;dn=Bikini-Pleasure.14.01.27.Gabrielle.Frolic.XXX.iMAGESET-YAPG&amp;tr=udp%3A%2F%2Ftracker.openbittorrent.com%3A80&amp;tr=udp%3A%2F%2Fopen.demonii.com%3A1337&amp;tr=udp%3A%2F%2Ftracker.coppersurfer.tk%3A6969&amp;tr=udp%3A%2F%2Fexodus.desync.com%3A6969","seeders":0,"leechers":0,"uploader":"Drarbg","files":131,"time":1390818395,"description":"Bikini-Pleasure.com_14.01.27.Gabrielle.Frolic.XXX.iMAGESET-YAPG\n","torrent":{"xt":"urn:btih:0b8216e1edb7573a8f309e46683246b73a71fa38","amp;dn":"Bikini-Pleasure.14.01.27.Gabrielle.Frolic.XXX.iMAGESET-YAPG","amp;tr":["udp%3A%2F%2Ftracker.openbittorrent.com%3A80","udp%3A%2F%2Fopen.demonii.com%3A1337","udp%3A%2F%2Ftracker.coppersurfer.tk%3A6969","udp%3A%2F%2Fexodus.desync.com%3A6969"],"infoHash":"0b8216e1edb7573a8f309e46683246b73a71fa38","infoHashBuffer":{"type":"Buffer","data":[11,130,22,225,237,183,87,58,143,48,158,70,104,50,70,183,58,113,250,56]},"announce":[],"urlList":[]}}