{"title":"[RealExGirlfriends] Chloe Amour (Back To School Special / 05.24.","uid":10216310,"size":659619264,"categoryP":"porn","categoryS":"other","magnet":"?xt=urn:btih:0cff5d3122c4839c43f2559f467c2cc827f3c704&amp;dn=%5BRealExGirlfriends%5D+Chloe+Amour+%28Back+To+School+Special+%2F+05.24.&amp;tr=udp%3A%2F%2Ftracker.openbittorrent.com%3A80&amp;tr=udp%3A%2F%2Fopen.demonii.com%3A1337&amp;tr=udp%3A%2F%2Ftracker.coppersurfer.tk%3A6969&amp;tr=udp%3A%2F%2Fexodus.desync.com%3A6969","seeders":0,"leechers":1,"uploader":"SBXero","files":1,"time":1400971843,"description":"[RealExGirlfriends] Chloe Amour (Back To School Special / 05.24.2014)","torrent":{"xt":"urn:btih:0cff5d3122c4839c43f2559f467c2cc827f3c704","amp;dn":"%5BRealExGirlfriends%5D+Chloe+Amour+%28Back+To+School+Special+%2F+05.24.","amp;tr":["udp%3A%2F%2Ftracker.openbittorrent.com%3A80","udp%3A%2F%2Fopen.demonii.com%3A1337","udp%3A%2F%2Ftracker.coppersurfer.tk%3A6969","udp%3A%2F%2Fexodus.desync.com%3A6969"],"infoHash":"0cff5d3122c4839c43f2559f467c2cc827f3c704","infoHashBuffer":{"type":"Buffer","data":[12,255,93,49,34,196,131,156,67,242,85,159,70,124,44,200,39,243,199,4]},"announce":[],"urlList":[]}}