{"title":"ATK Set 292199 - Candelaria Gallery 253 Latinas","uid":9478549,"size":134628735,"categoryP":"porn","categoryS":"pictures","magnet":"?xt=urn:btih:127c5dad47168113642d998ddedd06cee31f4e3e&amp;dn=ATK+Set+292199+-+Candelaria+Gallery+253+Latinas&amp;tr=udp%3A%2F%2Ftracker.openbittorrent.com%3A80&amp;tr=udp%3A%2F%2Fopen.demonii.com%3A1337&amp;tr=udp%3A%2F%2Ftracker.coppersurfer.tk%3A6969&amp;tr=udp%3A%2F%2Fexodus.desync.com%3A6969","seeders":0,"leechers":1,"uploader":"bestec1234","files":105,"time":1389747826,"description":" &lt;a href=&quot;\nhttp://bayimg.com/bagAIaAFp&quot; rel=&quot;nofollow&quot; target=&quot;_NEW&quot;&gt;\nhttp://bayimg.com/bagAIaAFp&lt;/a&gt; &lt;a href=&quot;\nhttp://bayimg.com/BAGAjAaFP&quot; rel=&quot;nofollow&quot; target=&quot;_NEW&quot;&gt;\nhttp://bayimg.com/BAGAjAaFP&lt;/a&gt; &lt;a href=&quot;\nhttp://bayimg.com/BagakaaFp&quot; rel=&quot;nofollow&quot; target=&quot;_NEW&quot;&gt;\nhttp://bayimg.com/BagakaaFp&lt;/a&gt; &lt;a href=&quot;\nhttp://bayimg.com/bAgALAafP&quot; rel=&quot;nofollow&quot; target=&quot;_NEW&quot;&gt;\nhttp://bayimg.com/bAgALAafP&lt;/a&gt;\n\nAge: 33\nHair Color: black\nModel Number: can057","torrent":{"xt":"urn:btih:127c5dad47168113642d998ddedd06cee31f4e3e","amp;dn":"ATK+Set+292199+-+Candelaria+Gallery+253+Latinas","amp;tr":["udp%3A%2F%2Ftracker.openbittorrent.com%3A80","udp%3A%2F%2Fopen.demonii.com%3A1337","udp%3A%2F%2Ftracker.coppersurfer.tk%3A6969","udp%3A%2F%2Fexodus.desync.com%3A6969"],"infoHash":"127c5dad47168113642d998ddedd06cee31f4e3e","infoHashBuffer":{"type":"Buffer","data":[18,124,93,173,71,22,129,19,100,45,153,141,222,221,6,206,227,31,78,62]},"announce":[],"urlList":[]}}