{"title":"Desert.Heat.XXX.720p.BluRay.x264-CHiKANi","uid":10208112,"size":3552581349,"categoryP":"porn","categoryS":"other","magnet":"?xt=urn:btih:1418d03a0354693e676378d0775d20d9eadc46f4&amp;dn=Desert.Heat.XXX.720p.BluRay.x264-CHiKANi&amp;tr=udp%3A%2F%2Ftracker.openbittorrent.com%3A80&amp;tr=udp%3A%2F%2Fopen.demonii.com%3A1337&amp;tr=udp%3A%2F%2Ftracker.coppersurfer.tk%3A6969&amp;tr=udp%3A%2F%2Fexodus.desync.com%3A6969","seeders":0,"leechers":2,"uploader":"Drarbg","files":4,"time":1400878337,"description":"Desert.Heat.XXX.720p.BluRay.x264-CHiKANi\n-----------------------------------------\nScreens : &lt;a href=&quot;\nhttp://imagecurl.org/viewer.php?file=37083313556226447042.jpg&quot; rel=&quot;nofollow&quot; target=&quot;_NEW&quot;&gt;\nhttp://imagecurl.org/viewer.php?file=37083313556226447042.jpg&lt;/a&gt;\n\n","torrent":{"xt":"urn:btih:1418d03a0354693e676378d0775d20d9eadc46f4","amp;dn":"Desert.Heat.XXX.720p.BluRay.x264-CHiKANi","amp;tr":["udp%3A%2F%2Ftracker.openbittorrent.com%3A80","udp%3A%2F%2Fopen.demonii.com%3A1337","udp%3A%2F%2Ftracker.coppersurfer.tk%3A6969","udp%3A%2F%2Fexodus.desync.com%3A6969"],"infoHash":"1418d03a0354693e676378d0775d20d9eadc46f4","infoHashBuffer":{"type":"Buffer","data":[20,24,208,58,3,84,105,62,103,99,120,208,119,93,32,217,234,220,70,244]},"announce":[],"urlList":[]}}