{"title":"VANDR-095 amateur JAV CENSORED","uid":9602072,"size":1892534357,"categoryP":"porn","categoryS":"movie_clips","magnet":"?xt=urn:btih:1d8f70e5be3d23dbf6a975e48160b80e19f4eac0&amp;dn=VANDR-095+amateur+JAV+CENSORED&amp;tr=udp%3A%2F%2Ftracker.openbittorrent.com%3A80&amp;tr=udp%3A%2F%2Fopen.demonii.com%3A1337&amp;tr=udp%3A%2F%2Ftracker.coppersurfer.tk%3A6969&amp;tr=udp%3A%2F%2Fexodus.desync.com%3A6969","seeders":0,"leechers":2,"uploader":"3xplanet","files":1,"time":1392135484,"description":"VANDR-095 amateur JAV CENSORED\nCover &lt;a href=&quot;\nhttp://www.3xplanet.com/view/28215.html&quot; rel=&quot;nofollow&quot; target=&quot;_NEW&quot;&gt;\nhttp://www.3xplanet.com/view/28215.html&lt;/a&gt;\nScreenshot &lt;a href=&quot;\nhttp://www.3xplanet.com/view/28261.html&quot; rel=&quot;nofollow&quot; target=&quot;_NEW&quot;&gt;\nhttp://www.3xplanet.com/view/28261.html&lt;/a&gt;\nTitle: \nStarring: amateur\nStudio:  V &amp; R Products\n\nTag: JAV, CENSORED, V &amp; R Products, \n\n","torrent":{"xt":"urn:btih:1d8f70e5be3d23dbf6a975e48160b80e19f4eac0","amp;dn":"VANDR-095+amateur+JAV+CENSORED","amp;tr":["udp%3A%2F%2Ftracker.openbittorrent.com%3A80","udp%3A%2F%2Fopen.demonii.com%3A1337","udp%3A%2F%2Ftracker.coppersurfer.tk%3A6969","udp%3A%2F%2Fexodus.desync.com%3A6969"],"infoHash":"1d8f70e5be3d23dbf6a975e48160b80e19f4eac0","infoHashBuffer":{"type":"Buffer","data":[29,143,112,229,190,61,35,219,246,169,117,228,129,96,184,14,25,244,234,192]},"announce":[],"urlList":[]}}