{"title":"ATK Set 292102 - Julia Gallery 342 Over 40","uid":9490358,"size":131032631,"categoryP":"porn","categoryS":"pictures","magnet":"?xt=urn:btih:22d93b5ee694773bd1d39d6fc3803db5733b30e6&amp;dn=ATK+Set+292102+-+Julia+Gallery+342+Over+40&amp;tr=udp%3A%2F%2Ftracker.openbittorrent.com%3A80&amp;tr=udp%3A%2F%2Fopen.demonii.com%3A1337&amp;tr=udp%3A%2F%2Ftracker.coppersurfer.tk%3A6969&amp;tr=udp%3A%2F%2Fexodus.desync.com%3A6969","seeders":0,"leechers":2,"uploader":"bestec1234","files":-1,"time":1389985432,"description":" &lt;a href=&quot;\nhttp://bayimg.com/eAhODaAfB&quot; rel=&quot;nofollow&quot; target=&quot;_NEW&quot;&gt;\nhttp://bayimg.com/eAhODaAfB&lt;/a&gt; &lt;a href=&quot;\nhttp://bayimg.com/eAHOeaAFb&quot; rel=&quot;nofollow&quot; target=&quot;_NEW&quot;&gt;\nhttp://bayimg.com/eAHOeaAFb&lt;/a&gt; &lt;a href=&quot;\nhttp://bayimg.com/eAHoFAAfB&quot; rel=&quot;nofollow&quot; target=&quot;_NEW&quot;&gt;\nhttp://bayimg.com/eAHoFAAfB&lt;/a&gt; &lt;a href=&quot;\nhttp://bayimg.com/EaHogAAfb&quot; rel=&quot;nofollow&quot; target=&quot;_NEW&quot;&gt;\nhttp://bayimg.com/EaHogAAfb&lt;/a&gt; &lt;a href=&quot;\nhttp://bayimg.com/eahOHaafb&quot; rel=&quot;nofollow&quot; target=&quot;_NEW&quot;&gt;\nhttp://bayimg.com/eahOHaafb&lt;/a&gt; &lt;a href=&quot;\nhttp://bayimg.com/EAhoiAaFb&quot; rel=&quot;nofollow&quot; target=&quot;_NEW&quot;&gt;\nhttp://bayimg.com/EAhoiAaFb&lt;/a&gt; &lt;a href=&quot;\nhttp://bayimg.com/eahoJAAFB&quot; rel=&quot;nofollow&quot; target=&quot;_NEW&quot;&gt;\nhttp://bayimg.com/eahoJAAFB&lt;/a&gt; &lt;a href=&quot;\nhttp://bayimg.com/eahokaAFB&quot; rel=&quot;nofollow&quot; target=&quot;_NEW&quot;&gt;\nhttp://bayimg.com/eahokaAFB&lt;/a&gt;\n\nAge: 45\nHair Color: red\nModel Number: jul074","torrent":{"xt":"urn:btih:22d93b5ee694773bd1d39d6fc3803db5733b30e6","amp;dn":"ATK+Set+292102+-+Julia+Gallery+342+Over+40","amp;tr":["udp%3A%2F%2Ftracker.openbittorrent.com%3A80","udp%3A%2F%2Fopen.demonii.com%3A1337","udp%3A%2F%2Ftracker.coppersurfer.tk%3A6969","udp%3A%2F%2Fexodus.desync.com%3A6969"],"infoHash":"22d93b5ee694773bd1d39d6fc3803db5733b30e6","infoHashBuffer":{"type":"Buffer","data":[34,217,59,94,230,148,119,59,209,211,157,111,195,128,61,181,115,59,48,230]},"announce":[],"urlList":[]}}