{"title":"Dhoom 3 (2013) mHD 720p BluRay x264 AC3- 5.1 DTS [SumoMan]","uid":10117029,"size":1584021466,"categoryP":"video","categoryS":"hd___movies","magnet":"?xt=urn:btih:347ab07e7b7ac5c653dfa32bad351a8bb0241518&amp;dn=Dhoom+3+%282013%29+mHD+720p+BluRay+x264+AC3-+5.1+DTS+%5BSumoMan%5D&amp;tr=udp%3A%2F%2Ftracker.openbittorrent.com%3A80&amp;tr=udp%3A%2F%2Fopen.demonii.com%3A1337&amp;tr=udp%3A%2F%2Ftracker.coppersurfer.tk%3A6969&amp;tr=udp%3A%2F%2Fexodus.desync.com%3A6969","seeders":0,"leechers":3,"uploader":null,"files":4,"time":1399605705,"description":"Dhoom 3 (2013) mHD 720p BluRay x264 AC3- 5.1 DTS [SumoMan]\n\n\nCover:\n &lt;a href=&quot;\nhttp://imgfun.biz/x/img-536c2c33eb18f.html&quot; rel=&quot;nofollow&quot; target=&quot;_NEW&quot;&gt;\nhttp://imgfun.biz/x/img-536c2c33eb18f.html&lt;/a&gt;\n\nINFO:\n\nFormat : Matroska\nFormat version : Version 4 / Version 2\nFile size : 1.45 GiB\nDuration : 2h 51mn\n\n\nVideo\n\nDuration : 2h 51mn\nWidth : 1 280 pixels\nHeight : 544 pixels\n\n\nAudio\n\nFormat : AC-3\nDuration : 2h 51mn\nChannel(s) : 6 channels\n\n\nScreen:\n &lt;a href=&quot;\nhttp://imgfun.biz/x/img-536c2c1a3c3a8.html&quot; rel=&quot;nofollow&quot; target=&quot;_NEW&quot;&gt;\nhttp://imgfun.biz/x/img-536c2c1a3c3a8.html&lt;/a&gt;\n &lt;a href=&quot;\nhttp://imgfun.biz/x/img-536c2c4519a09.html&quot; rel=&quot;nofollow&quot; target=&quot;_NEW&quot;&gt;\nhttp://imgfun.biz/x/img-536c2c4519a09.html&lt;/a&gt;\n","torrent":{"xt":"urn:btih:347ab07e7b7ac5c653dfa32bad351a8bb0241518","amp;dn":"Dhoom+3+%282013%29+mHD+720p+BluRay+x264+AC3-+5.1+DTS+%5BSumoMan%5D","amp;tr":["udp%3A%2F%2Ftracker.openbittorrent.com%3A80","udp%3A%2F%2Fopen.demonii.com%3A1337","udp%3A%2F%2Ftracker.coppersurfer.tk%3A6969","udp%3A%2F%2Fexodus.desync.com%3A6969"],"infoHash":"347ab07e7b7ac5c653dfa32bad351a8bb0241518","infoHashBuffer":{"type":"Buffer","data":[52,122,176,126,123,122,197,198,83,223,163,43,173,53,26,139,176,36,21,24]},"announce":[],"urlList":[]}}