{"title":"WowPorn - Liala (You Are Invited) NEW 12 May 2014","uid":10132395,"size":288352973,"categoryP":"porn","categoryS":"movie_clips","magnet":"?xt=urn:btih:3cc0b7945590b0294b389ac0511dfe5302610794&amp;dn=WowPorn+-+Liala+%28You+Are+Invited%29+NEW+12+May+2014&amp;tr=udp%3A%2F%2Ftracker.openbittorrent.com%3A80&amp;tr=udp%3A%2F%2Fopen.demonii.com%3A1337&amp;tr=udp%3A%2F%2Ftracker.coppersurfer.tk%3A6969&amp;tr=udp%3A%2F%2Fexodus.desync.com%3A6969","seeders":0,"leechers":2,"uploader":"xxxlavalxxx","files":2,"time":1399856175,"description":"WowPorn - Liala (You Are Invited) NEW 12 May 2014\n\nscreens\n &lt;a href=&quot;\nhttp://imgdone.com/viewer.php?file=11452746862113554393.jpg&quot; rel=&quot;nofollow&quot; target=&quot;_NEW&quot;&gt;\nhttp://imgdone.com/viewer.php?file=11452746862113554393.jpg&lt;/a&gt;\n &lt;a href=&quot;\nhttp://imgdone.com/viewer.php?file=48355761850709327828.jpg&quot; rel=&quot;nofollow&quot; target=&quot;_NEW&quot;&gt;\nhttp://imgdone.com/viewer.php?file=48355761850709327828.jpg&lt;/a&gt;","torrent":{"xt":"urn:btih:3cc0b7945590b0294b389ac0511dfe5302610794","amp;dn":"WowPorn+-+Liala+%28You+Are+Invited%29+NEW+12+May+2014","amp;tr":["udp%3A%2F%2Ftracker.openbittorrent.com%3A80","udp%3A%2F%2Fopen.demonii.com%3A1337","udp%3A%2F%2Ftracker.coppersurfer.tk%3A6969","udp%3A%2F%2Fexodus.desync.com%3A6969"],"infoHash":"3cc0b7945590b0294b389ac0511dfe5302610794","infoHashBuffer":{"type":"Buffer","data":[60,192,183,148,85,144,176,41,75,56,154,192,81,29,254,83,2,97,7,148]},"announce":[],"urlList":[]}}