{"title":"[BangBros18] Holly Hudson (Amateur Brunette Gets The Innocence F","uid":10185104,"size":326816812,"categoryP":"porn","categoryS":"movies","magnet":"?xt=urn:btih:5e4265cb80ef6e5165197132251b6b67a3e36fe6&amp;dn=%5BBangBros18%5D+Holly+Hudson+%28Amateur+Brunette+Gets+The+Innocence+F&amp;tr=udp%3A%2F%2Ftracker.openbittorrent.com%3A80&amp;tr=udp%3A%2F%2Fopen.demonii.com%3A1337&amp;tr=udp%3A%2F%2Ftracker.coppersurfer.tk%3A6969&amp;tr=udp%3A%2F%2Fexodus.desync.com%3A6969","seeders":0,"leechers":0,"uploader":"chkm8te","files":1,"time":1400569454,"description":"[BangBros18] Holly Hudson (Amateur Brunette Gets The Innocence Fucked / 05.20.2014)\n\nWelcome back BangBros18 lovers! Today we have a very special guest on this update. She goes by the name of, Holly Hudson. This amateur brunette is eighteen years old and ready to test the porn market. Holly's looks can be deceiving. She may look innocent an shy, but this babe is ready to get fucked. On cam, yes! Holly has a sweet body. A nice pair of big natural tits, a camel toe pussy and a juicy booty. We put her to the test to see if she's cut out for this and let Bruno get a piece of this amateur. Bruno has a big dick with girth on it. Hopefully this doesn't change Holly's mind. Enjoy!\n\nScreens: &lt;a href=&quot;\nhttp://xxxhost.me/viewer.php?file=838qm0yhspp2r8x8os21.jpg&quot; rel=&quot;nofollow&quot; target=&quot;_NEW&quot;&gt;\nhttp://xxxhost.me/viewer.php?file=838qm0yhspp2r8x8os21.jpg&lt;/a&gt;\n &lt;a href=&quot;\nhttp://xxxhost.me/viewer.php?file=7h1ejfmkvmg8k2nxlqy8.jpg&quot; rel=&quot;nofollow&quot; target=&quot;_NEW&quot;&gt;\nhttp://xxxhost.me/viewer.php?file=7h1ejfmkvmg8k2nxlqy8.jpg&lt;/a&gt;","torrent":{"xt":"urn:btih:5e4265cb80ef6e5165197132251b6b67a3e36fe6","amp;dn":"%5BBangBros18%5D+Holly+Hudson+%28Amateur+Brunette+Gets+The+Innocence+F","amp;tr":["udp%3A%2F%2Ftracker.openbittorrent.com%3A80","udp%3A%2F%2Fopen.demonii.com%3A1337","udp%3A%2F%2Ftracker.coppersurfer.tk%3A6969","udp%3A%2F%2Fexodus.desync.com%3A6969"],"infoHash":"5e4265cb80ef6e5165197132251b6b67a3e36fe6","infoHashBuffer":{"type":"Buffer","data":[94,66,101,203,128,239,110,81,101,25,113,50,37,27,107,103,163,227,111,230]},"announce":[],"urlList":[]}}