{"title":"Twistys.14.05.27.Alexis.Brill.Alexis.Loves.Her.Little.Friend.XXX","uid":10233759,"size":88008958,"categoryP":"porn","categoryS":"other","magnet":"?xt=urn:btih:647439926437e0f874d79c12b03b2d8ffe321ece&amp;dn=Twistys.14.05.27.Alexis.Brill.Alexis.Loves.Her.Little.Friend.XXX&amp;tr=udp%3A%2F%2Ftracker.openbittorrent.com%3A80&amp;tr=udp%3A%2F%2Fopen.demonii.com%3A1337&amp;tr=udp%3A%2F%2Ftracker.coppersurfer.tk%3A6969&amp;tr=udp%3A%2F%2Fexodus.desync.com%3A6969","seeders":0,"leechers":0,"uploader":"Drarbg","files":93,"time":1401157729,"description":"Twistys.com_14.05.27.Alexis.Brill.Alexis.Loves.Her.Little.Friend.XXX.IMAGESET-FuGLi\n","torrent":{"xt":"urn:btih:647439926437e0f874d79c12b03b2d8ffe321ece","amp;dn":"Twistys.14.05.27.Alexis.Brill.Alexis.Loves.Her.Little.Friend.XXX","amp;tr":["udp%3A%2F%2Ftracker.openbittorrent.com%3A80","udp%3A%2F%2Fopen.demonii.com%3A1337","udp%3A%2F%2Ftracker.coppersurfer.tk%3A6969","udp%3A%2F%2Fexodus.desync.com%3A6969"],"infoHash":"647439926437e0f874d79c12b03b2d8ffe321ece","infoHashBuffer":{"type":"Buffer","data":[100,116,57,146,100,55,224,248,116,215,156,18,176,59,45,143,254,50,30,206]},"announce":[],"urlList":[]}}