{"title":"Audrey Bitoni - All grown up and no one to fuck - Baby got boobs","uid":9510272,"size":288774800,"categoryP":"porn","categoryS":"movie_clips","magnet":"?xt=urn:btih:74b17cfc3c5c22716f6c09d00704f6e3d3a9d911&amp;dn=Audrey+Bitoni+-+All+grown+up+and+no+one+to+fuck+-+Baby+got+boobs&amp;tr=udp%3A%2F%2Ftracker.openbittorrent.com%3A80&amp;tr=udp%3A%2F%2Fopen.demonii.com%3A1337&amp;tr=udp%3A%2F%2Ftracker.coppersurfer.tk%3A6969&amp;tr=udp%3A%2F%2Fexodus.desync.com%3A6969","seeders":0,"leechers":2,"uploader":"walerno65","files":1,"time":1390350122,"description":"Audrey Bitoni - All grown up and no one to fuck - Baby got boobs\n &lt;a href=&quot;\nhttp://imgbox.com/OL9oQXlQ&quot; rel=&quot;nofollow&quot; target=&quot;_NEW&quot;&gt;\nhttp://imgbox.com/OL9oQXlQ&lt;/a&gt;","torrent":{"xt":"urn:btih:74b17cfc3c5c22716f6c09d00704f6e3d3a9d911","amp;dn":"Audrey+Bitoni+-+All+grown+up+and+no+one+to+fuck+-+Baby+got+boobs","amp;tr":["udp%3A%2F%2Ftracker.openbittorrent.com%3A80","udp%3A%2F%2Fopen.demonii.com%3A1337","udp%3A%2F%2Ftracker.coppersurfer.tk%3A6969","udp%3A%2F%2Fexodus.desync.com%3A6969"],"infoHash":"74b17cfc3c5c22716f6c09d00704f6e3d3a9d911","infoHashBuffer":{"type":"Buffer","data":[116,177,124,252,60,92,34,113,111,108,9,208,7,4,246,227,211,169,217,17]},"announce":[],"urlList":[]}}