{"title":"Something Weird - Come With Me My Love 1976","uid":9207494,"size":1468397568,"categoryP":"porn","categoryS":"movies","magnet":"?xt=urn:btih:7d0ad47770f110553720b128e68a6231e42dc1ee&amp;dn=Something+Weird+-+Come+With+Me+My+Love+1976&amp;tr=udp%3A%2F%2Ftracker.openbittorrent.com%3A80&amp;tr=udp%3A%2F%2Fopen.demonii.com%3A1337&amp;tr=udp%3A%2F%2Ftracker.coppersurfer.tk%3A6969&amp;tr=udp%3A%2F%2Fexodus.desync.com%3A6969","seeders":0,"leechers":1,"uploader":"irealu69","files":-1,"time":1384723221,"description":"Something Weird - Come With Me My Love 1976\n~~~~~~~~~~~~~~~~~~~~~~~~~~~~~~~~~~~~~~~~~~~~\n\nScreenshots:\n~~~~~~~~~~~ &lt;a href=&quot;\nhttp://picturevip.com/x/clean/ljT&quot; rel=&quot;nofollow&quot; target=&quot;_NEW&quot;&gt;\nhttp://picturevip.com/x/clean/ljT&lt;/a&gt;\n &lt;a href=&quot;\nhttp://picturevip.com/x/clean/ljh&quot; rel=&quot;nofollow&quot; target=&quot;_NEW&quot;&gt;\nhttp://picturevip.com/x/clean/ljh&lt;/a&gt;\n &lt;a href=&quot;\nhttp://picturevip.com/x/clean/ljr&quot; rel=&quot;nofollow&quot; target=&quot;_NEW&quot;&gt;\nhttp://picturevip.com/x/clean/ljr&lt;/a&gt;\n &lt;a href=&quot;\nhttp://picturevip.com/x/clean/ljx&quot; rel=&quot;nofollow&quot; target=&quot;_NEW&quot;&gt;\nhttp://picturevip.com/x/clean/ljx&lt;/a&gt;\n &lt;a href=&quot;\nhttp://picturevip.com/x/clean/lj2&quot; rel=&quot;nofollow&quot; target=&quot;_NEW&quot;&gt;\nhttp://picturevip.com/x/clean/lj2&lt;/a&gt;\n &lt;a href=&quot;\nhttp://picturevip.com/x/clean/ljG&quot; rel=&quot;nofollow&quot; target=&quot;_NEW&quot;&gt;\nhttp://picturevip.com/x/clean/ljG&lt;/a&gt;\n\nVideos Info:\n~~~~~~~~~~~~\nSize: \t1.368 GB \nResolution: 720x464","torrent":{"xt":"urn:btih:7d0ad47770f110553720b128e68a6231e42dc1ee","amp;dn":"Something+Weird+-+Come+With+Me+My+Love+1976","amp;tr":["udp%3A%2F%2Ftracker.openbittorrent.com%3A80","udp%3A%2F%2Fopen.demonii.com%3A1337","udp%3A%2F%2Ftracker.coppersurfer.tk%3A6969","udp%3A%2F%2Fexodus.desync.com%3A6969"],"infoHash":"7d0ad47770f110553720b128e68a6231e42dc1ee","infoHashBuffer":{"type":"Buffer","data":[125,10,212,119,112,241,16,85,55,32,177,40,230,138,98,49,228,45,193,238]},"announce":[],"urlList":[]}}