{"title":"Teenage.Rampage.12.XXX.DVDRip.x264-UPPERCUT","uid":9210276,"size":1542662247,"categoryP":"porn","categoryS":"movies","magnet":"?xt=urn:btih:80f5d74d1f0db36be347d787655c98b96a21a5fd&amp;dn=Teenage.Rampage.12.XXX.DVDRip.x264-UPPERCUT&amp;tr=udp%3A%2F%2Ftracker.openbittorrent.com%3A80&amp;tr=udp%3A%2F%2Fopen.demonii.com%3A1337&amp;tr=udp%3A%2F%2Ftracker.coppersurfer.tk%3A6969&amp;tr=udp%3A%2F%2Fexodus.desync.com%3A6969","seeders":0,"leechers":1,"uploader":"xxxlavalxxx","files":4,"time":1384771802,"description":"Category\tAll Sex, Legal Teen, Porno Dan Presents' Teenage Rampage Series\n\nStarring\tLexi Belle, Britney Amber, Karmen Karma, Veronica Radke, Noelle Easton, Zoey Paige, Scarlett Lavey, Dallas Vick\n\nWhat do you get if you let 4 girls into a porn studio with Porno Dan? A Teenage Rampage!!!\n\n\n\t &lt;a href=&quot;\nhttp://imgdone.com/viewer.php?file=58876467448323183509.jpg&quot; rel=&quot;nofollow&quot; target=&quot;_NEW&quot;&gt;\nhttp://imgdone.com/viewer.php?file=58876467448323183509.jpg&lt;/a&gt;\n    \t &lt;a href=&quot;\nhttp://imgdone.com/viewer.php?file=81135628499154911841.jpg&quot; rel=&quot;nofollow&quot; target=&quot;_NEW&quot;&gt;\nhttp://imgdone.com/viewer.php?file=81135628499154911841.jpg&lt;/a&gt;\n    \t &lt;a href=&quot;\nhttp://imgdone.com/viewer.php?file=31875320573309386817.jpeg&quot; rel=&quot;nofollow&quot; target=&quot;_NEW&quot;&gt;\nhttp://imgdone.com/viewer.php?file=31875320573309386817.jpeg&lt;/a&gt;","torrent":{"xt":"urn:btih:80f5d74d1f0db36be347d787655c98b96a21a5fd","amp;dn":"Teenage.Rampage.12.XXX.DVDRip.x264-UPPERCUT","amp;tr":["udp%3A%2F%2Ftracker.openbittorrent.com%3A80","udp%3A%2F%2Fopen.demonii.com%3A1337","udp%3A%2F%2Ftracker.coppersurfer.tk%3A6969","udp%3A%2F%2Fexodus.desync.com%3A6969"],"infoHash":"80f5d74d1f0db36be347d787655c98b96a21a5fd","infoHashBuffer":{"type":"Buffer","data":[128,245,215,77,31,13,179,107,227,71,215,135,101,92,152,185,106,33,165,253]},"announce":[],"urlList":[]}}