{"title":"[LadyboysHeaven] Trantastic Asians Feat. TT (09.05.14) 1080p","uid":10196705,"size":991850312,"categoryP":"porn","categoryS":"hd___movies","magnet":"?xt=urn:btih:81ba0b1969ef232e3dc852177b5a9d6841de7075&amp;dn=%5BLadyboysHeaven%5D+Trantastic+Asians+Feat.+TT+%2809.05.14%29+1080p&amp;tr=udp%3A%2F%2Ftracker.openbittorrent.com%3A80&amp;tr=udp%3A%2F%2Fopen.demonii.com%3A1337&amp;tr=udp%3A%2F%2Ftracker.coppersurfer.tk%3A6969&amp;tr=udp%3A%2F%2Fexodus.desync.com%3A6969","seeders":0,"leechers":1,"uploader":"Zbeast","files":-1,"time":1400701611,"description":"Ladyboy TT getting fucked hard bareback....\n\nDuration: 00:25:45\nVideo: AVC (AVC) 1920x1080 25.00fps 5006kbps\nAudio: AAC (AAC LC) 110 kb/s 44.1KHz (2 chnls)\n\nScreens:\n======== &lt;a href=&quot;\nhttp://postimg.org/image/bz85nm5zh/&quot; rel=&quot;nofollow&quot; target=&quot;_NEW&quot;&gt;\nhttp://postimg.org/image/bz85nm5zh/&lt;/a&gt; &lt;a href=&quot;\nhttp://postimg.org/image/69rx3azt9/&quot; rel=&quot;nofollow&quot; target=&quot;_NEW&quot;&gt;\nhttp://postimg.org/image/69rx3azt9/&lt;/a&gt;","torrent":{"xt":"urn:btih:81ba0b1969ef232e3dc852177b5a9d6841de7075","amp;dn":"%5BLadyboysHeaven%5D+Trantastic+Asians+Feat.+TT+%2809.05.14%29+1080p","amp;tr":["udp%3A%2F%2Ftracker.openbittorrent.com%3A80","udp%3A%2F%2Fopen.demonii.com%3A1337","udp%3A%2F%2Ftracker.coppersurfer.tk%3A6969","udp%3A%2F%2Fexodus.desync.com%3A6969"],"infoHash":"81ba0b1969ef232e3dc852177b5a9d6841de7075","infoHashBuffer":{"type":"Buffer","data":[129,186,11,25,105,239,35,46,61,200,82,23,123,90,157,104,65,222,112,117]},"announce":[],"urlList":[]}}