{"title":"X-O Manowar 025 (2014) (Digital) (Darkness-Empire).cbr","uid":10200569,"size":100005752,"categoryP":"other","categoryS":"comics","magnet":"?xt=urn:btih:8fbc6dfe3e98e0fdde8ad21b53aaae124c0821b2&amp;dn=X-O+Manowar+025+%282014%29+%28Digital%29+%28Darkness-Empire%29.cbr&amp;tr=udp%3A%2F%2Ftracker.openbittorrent.com%3A80&amp;tr=udp%3A%2F%2Fopen.demonii.com%3A1337&amp;tr=udp%3A%2F%2Ftracker.coppersurfer.tk%3A6969&amp;tr=udp%3A%2F%2Fexodus.desync.com%3A6969","seeders":0,"leechers":0,"uploader":"nemesis43","files":1,"time":1400770673,"description":"X-O Manowar 025 (2014) (Digital) (Darkness-Empire)","torrent":{"xt":"urn:btih:8fbc6dfe3e98e0fdde8ad21b53aaae124c0821b2","amp;dn":"X-O+Manowar+025+%282014%29+%28Digital%29+%28Darkness-Empire%29.cbr","amp;tr":["udp%3A%2F%2Ftracker.openbittorrent.com%3A80","udp%3A%2F%2Fopen.demonii.com%3A1337","udp%3A%2F%2Ftracker.coppersurfer.tk%3A6969","udp%3A%2F%2Fexodus.desync.com%3A6969"],"infoHash":"8fbc6dfe3e98e0fdde8ad21b53aaae124c0821b2","infoHashBuffer":{"type":"Buffer","data":[143,188,109,254,62,152,224,253,222,138,210,27,83,170,174,18,76,8,33,178]},"announce":[],"urlList":[]}}