{"title":"Alex Jones Show - 2014 Feb 12 WE [sebaygo1]","uid":9607908,"size":68426035,"categoryP":"other","categoryS":"other","magnet":"?xt=urn:btih:911efa7db6eda615f7890fdc080d54c0ff9e374d&amp;dn=Alex+Jones+Show+-+2014+Feb+12+WE+%5Bsebaygo1%5D&amp;tr=udp%3A%2F%2Ftracker.openbittorrent.com%3A80&amp;tr=udp%3A%2F%2Fopen.demonii.com%3A1337&amp;tr=udp%3A%2F%2Ftracker.coppersurfer.tk%3A6969&amp;tr=udp%3A%2F%2Fexodus.desync.com%3A6969","seeders":0,"leechers":0,"uploader":"sebaygo1","files":12,"time":1392249248,"description":"\nThe Alex Jones Show \nWednesday, 12 February 2014\n\n\n[sebaygo1]\n\n\nShow Description\n................\nFrom the Infowars web site :: On the Wednesday, February 12 broadcast of The Alex Jones Show, Alex breaks down the stock market's heavy reliance upon the fed's QE bond buying stimulus and easy money printing schemes, as the market reacts eerily similar to how it did right before the stock market crash of 1929 which ushered in the Great Depression. \n\nOn today's show, Alex speaks with American economist and Assistant Secretary of the Treasury in the Reagan Administration, Paul Craig Roberts, about how Washington funded NGOs are purposely attempting to deliver Ukraine into the clutches of the EU. \n\nJones also discusses the very real prospect of engaging in war with China, Russia or Iran with renowned international trends forecaster and publisher of the Trends Journal, Gerald Celente. \n\nWe'll also cover why it's better to be a prepper in Atlanta during a snowstorm, the possibility of coordinated attacks on the power grid, and other hot news items.\n\n\n\n\n#%#%#%#%#%#%#%#%#%#%#%#%#%#%#%#%#%#%#%#%#%#%#%#%#%#%#\nNot able to find a torrent of mine where or when you \nexpected it?\nCheck out my torrents blog for info about what I am\nuploading, tracker problems, etc..\n\nSome sites will not allow a blogspot URL in an \nuploaded torrent's description, so I have included \nthe blog's web address in a file included with this\ntorrent named:\nsebaygo1_TorrentsAndBlogInfo_ver2.pdf\n#%#%#%#%#%#%#%#%#%#%#%#%#%#%#%#%#%#%#%#%#%#%#%#%#%#%#\n\n\n\n_/_/_/_/_/_/_/_/_/_/_/_/_/_/_/_/_/_/_/_/_/_/_/_/_/_/_/_/_/_/_/_/_/_/\n\n It is my opinion that in this time it is virtually\n essential to seek information from a variety of sources, \n to listen to a spectrum of voices in order to better \n understand the &quot;big picture.&quot; A reliance solely upon\n mainstream corporate media for news and info is a \n prescription for ignorance. I try to share information\n that counters the monotone of mainstream corporate media.\n \n NOTE: The material here is made available strictly as\n information. Do not assume my support for or endorsement \n of the contents. \n\n Think for yourself!\n To paraphrase the late William Cooper: \n Read everything, listen to everything, but believe nothing \n until you've researched it yourself.\n\n !! please try some of the other shows I upload too !!\n\n_/_/_/_/_/_/_/_/_/_/_/_/_/_/_/_/_/_/_/_/_/_/_/_/_/_/_/_/_/_/_/_/_/\n.","torrent":{"xt":"urn:btih:911efa7db6eda615f7890fdc080d54c0ff9e374d","amp;dn":"Alex+Jones+Show+-+2014+Feb+12+WE+%5Bsebaygo1%5D","amp;tr":["udp%3A%2F%2Ftracker.openbittorrent.com%3A80","udp%3A%2F%2Fopen.demonii.com%3A1337","udp%3A%2F%2Ftracker.coppersurfer.tk%3A6969","udp%3A%2F%2Fexodus.desync.com%3A6969"],"infoHash":"911efa7db6eda615f7890fdc080d54c0ff9e374d","infoHashBuffer":{"type":"Buffer","data":[145,30,250,125,182,237,166,21,247,137,15,220,8,13,84,192,255,158,55,77]},"announce":[],"urlList":[]}}