{"title":"Gabriella.Fox.Sexy.Hot.XXX.1080p.WEBRip.MP4-OHRLY","uid":10363599,"size":5497152838,"categoryP":"porn","categoryS":"other","magnet":"?xt=urn:btih:9a0a7338403521b116c5cb02eb0dd48567f4ba63&amp;dn=Gabriella.Fox.Sexy.Hot.XXX.1080p.WEBRip.MP4-OHRLY&amp;tr=udp%3A%2F%2Ftracker.openbittorrent.com%3A80&amp;tr=udp%3A%2F%2Fopen.demonii.com%3A1337&amp;tr=udp%3A%2F%2Ftracker.coppersurfer.tk%3A6969&amp;tr=udp%3A%2F%2Fexodus.desync.com%3A6969","seeders":0,"leechers":2,"uploader":"Drarbg","files":6,"time":1402846094,"description":"Gabriella.Fox.Sexy.Hot.XXX.1080p.WEBRip.MP4-OHRLY\n-----------------------------------------\nScreens : &lt;a href=&quot;\nhttp://imagecurl.org/viewer.php?file=00877084523777634323.jpg&quot; rel=&quot;nofollow&quot; target=&quot;_NEW&quot;&gt;\nhttp://imagecurl.org/viewer.php?file=00877084523777634323.jpg&lt;/a&gt;\n\n","torrent":{"xt":"urn:btih:9a0a7338403521b116c5cb02eb0dd48567f4ba63","amp;dn":"Gabriella.Fox.Sexy.Hot.XXX.1080p.WEBRip.MP4-OHRLY","amp;tr":["udp%3A%2F%2Ftracker.openbittorrent.com%3A80","udp%3A%2F%2Fopen.demonii.com%3A1337","udp%3A%2F%2Ftracker.coppersurfer.tk%3A6969","udp%3A%2F%2Fexodus.desync.com%3A6969"],"infoHash":"9a0a7338403521b116c5cb02eb0dd48567f4ba63","infoHashBuffer":{"type":"Buffer","data":[154,10,115,56,64,53,33,177,22,197,203,2,235,13,212,133,103,244,186,99]},"announce":[],"urlList":[]}}