{"title":"[HDMassagePorn] Ebba - Filthy Blue-haired Girl Massage (1080p) (","uid":9457977,"size":674227720,"categoryP":"porn","categoryS":"hd___movies","magnet":"?xt=urn:btih:b84943e16cf925c28ed4d74f5f84a647094677e2&amp;dn=%5BHDMassagePorn%5D+Ebba+-+Filthy+Blue-haired+Girl+Massage+%281080p%29+%28&amp;tr=udp%3A%2F%2Ftracker.openbittorrent.com%3A80&amp;tr=udp%3A%2F%2Fopen.demonii.com%3A1337&amp;tr=udp%3A%2F%2Ftracker.coppersurfer.tk%3A6969&amp;tr=udp%3A%2F%2Fexodus.desync.com%3A6969","seeders":0,"leechers":1,"uploader":"xuluhulu","files":1,"time":1389301935,"description":"You can tell this babe isn't the shy type! She's got lots of tattoos and blue hair, and when she came for a private massage session the massagist knew right away that he'd bang that chick. And as always, he was right! Sexy erotic massage ended up as a real wild orgy on the massage table!\n\nSCREENS:\n &lt;a href=&quot;\nhttp://www.imgnip.com/viewer.php?file=74326672621019799260.jpg&quot; rel=&quot;nofollow&quot; target=&quot;_NEW&quot;&gt;\nhttp://www.imgnip.com/viewer.php?file=74326672621019799260.jpg&lt;/a&gt;\n &lt;a href=&quot;\nhttp://www.imgnip.com/viewer.php?file=40301172900315352273.jpg&quot; rel=&quot;nofollow&quot; target=&quot;_NEW&quot;&gt;\nhttp://www.imgnip.com/viewer.php?file=40301172900315352273.jpg&lt;/a&gt;\n\n\nSEED &amp; ENJOY!!!\t","torrent":{"xt":"urn:btih:b84943e16cf925c28ed4d74f5f84a647094677e2","amp;dn":"%5BHDMassagePorn%5D+Ebba+-+Filthy+Blue-haired+Girl+Massage+%281080p%29+%28","amp;tr":["udp%3A%2F%2Ftracker.openbittorrent.com%3A80","udp%3A%2F%2Fopen.demonii.com%3A1337","udp%3A%2F%2Ftracker.coppersurfer.tk%3A6969","udp%3A%2F%2Fexodus.desync.com%3A6969"],"infoHash":"b84943e16cf925c28ed4d74f5f84a647094677e2","infoHashBuffer":{"type":"Buffer","data":[184,73,67,225,108,249,37,194,142,212,215,79,95,132,166,71,9,70,119,226]},"announce":[],"urlList":[]}}