{"title":"The.Lego.Movie.2014.HDRip.XviD-AQOS","uid":10195101,"size":945907661,"categoryP":"video","categoryS":"movies","magnet":"?xt=urn:btih:bc941fda79bc961ca648c0c8dbd89afb41314646&amp;dn=The.Lego.Movie.2014.HDRip.XviD-AQOS&amp;tr=udp%3A%2F%2Ftracker.openbittorrent.com%3A80&amp;tr=udp%3A%2F%2Fopen.demonii.com%3A1337&amp;tr=udp%3A%2F%2Ftracker.coppersurfer.tk%3A6969&amp;tr=udp%3A%2F%2Fexodus.desync.com%3A6969","seeders":0,"leechers":0,"uploader":"Xetron","files":4,"time":1400683777,"description":"[img]http://s16.postimg.org/z136lfev9/lego.png[/img]\n\nGENERAL iNFO \nTiTLE: The.Lego.Movie.2014.HDRip.XviD-AQOS\niMDB: http://www.imdb.com/title/tt1490017/\nFORMAT: AVi\nLENGTH: 1h 40mn\nSiZE: 887 MiB\nTYPE: HDRip\nPROFiLE: Advanced Simple@L5\nRESOLUTiON: 640 x 272 pixels\nASPECT RATiO: 2.35:1\nBiTRATE: 1 233 Kbps\nFRAMERATE: 23.976 fps\nSUBTITLE: N/A\nAUDiO: English MP3 2.0 @ 128 kbps\nSOURCE: 720p (thanks)\nENCODER: bLaNgKo\n\nScreens -\n[img]http://s16.postimg.org/sxlm1iolh/image.png[/img]\n[img]http://s16.postimg.org/buiu607wl/image.png[/img]\n[img]http://s16.postimg.org/aw2h3pukl/image.png[/img]","torrent":{"xt":"urn:btih:bc941fda79bc961ca648c0c8dbd89afb41314646","amp;dn":"The.Lego.Movie.2014.HDRip.XviD-AQOS","amp;tr":["udp%3A%2F%2Ftracker.openbittorrent.com%3A80","udp%3A%2F%2Fopen.demonii.com%3A1337","udp%3A%2F%2Ftracker.coppersurfer.tk%3A6969","udp%3A%2F%2Fexodus.desync.com%3A6969"],"infoHash":"bc941fda79bc961ca648c0c8dbd89afb41314646","infoHashBuffer":{"type":"Buffer","data":[188,148,31,218,121,188,150,28,166,72,192,200,219,216,154,251,65,49,70,70]},"announce":[],"urlList":[]}}