{"title":"Catwalk Poison Vol 49 Azusa Nagasawa 720p","uid":10304106,"size":4693981634,"categoryP":"porn","categoryS":"hd___movies","magnet":"?xt=urn:btih:c44281bcc8b70b50dcac8cb26deca48e721896f3&amp;dn=Catwalk+Poison+Vol+49+Azusa+Nagasawa+720p&amp;tr=udp%3A%2F%2Ftracker.openbittorrent.com%3A80&amp;tr=udp%3A%2F%2Fopen.demonii.com%3A1337&amp;tr=udp%3A%2F%2Ftracker.coppersurfer.tk%3A6969&amp;tr=udp%3A%2F%2Fexodus.desync.com%3A6969","seeders":0,"leechers":8,"uploader":"ExpoUrani","files":3,"time":1402013485,"description":"Screnner:\n &lt;a href=&quot;\nhttp://imadul.com/?2pm=AVBE&quot; rel=&quot;nofollow&quot; target=&quot;_NEW&quot;&gt;\nhttp://imadul.com/?2pm=AVBE&lt;/a&gt;\n\nSource of the torrent video:\n &lt;a href=&quot;\nhttp://serakon.com/8392-catwalk-poison-vol-49-azusa-nagasawa-720p.html&quot; rel=&quot;nofollow&quot; target=&quot;_NEW&quot;&gt;\nhttp://serakon.com/8392-catwalk-poison-vol-49-azusa-nagasawa-720p.html&lt;/a&gt;","torrent":{"xt":"urn:btih:c44281bcc8b70b50dcac8cb26deca48e721896f3","amp;dn":"Catwalk+Poison+Vol+49+Azusa+Nagasawa+720p","amp;tr":["udp%3A%2F%2Ftracker.openbittorrent.com%3A80","udp%3A%2F%2Fopen.demonii.com%3A1337","udp%3A%2F%2Ftracker.coppersurfer.tk%3A6969","udp%3A%2F%2Fexodus.desync.com%3A6969"],"infoHash":"c44281bcc8b70b50dcac8cb26deca48e721896f3","infoHashBuffer":{"type":"Buffer","data":[196,66,129,188,200,183,11,80,220,172,140,178,109,236,164,142,114,24,150,243]},"announce":[],"urlList":[]}}