{"title":"ATK Set 289087 - Alison Faye Gallery 2102013 Toys","uid":9224830,"size":87140570,"categoryP":"porn","categoryS":"pictures","magnet":"?xt=urn:btih:c540e1aeced837e5b225077834e43cbedd0f7214&amp;dn=ATK+Set+289087+-+Alison+Faye+Gallery+2102013+Toys&amp;tr=udp%3A%2F%2Ftracker.openbittorrent.com%3A80&amp;tr=udp%3A%2F%2Fopen.demonii.com%3A1337&amp;tr=udp%3A%2F%2Ftracker.coppersurfer.tk%3A6969&amp;tr=udp%3A%2F%2Fexodus.desync.com%3A6969","seeders":0,"leechers":1,"uploader":"bestec1234","files":-1,"time":1384993964,"description":" &lt;a href=&quot;\nhttp://bayimg.com/CAcgEaaFj&quot; rel=&quot;nofollow&quot; target=&quot;_NEW&quot;&gt;\nhttp://bayimg.com/CAcgEaaFj&lt;/a&gt; &lt;a href=&quot;\nhttp://bayimg.com/CAcGfAaFj&quot; rel=&quot;nofollow&quot; target=&quot;_NEW&quot;&gt;\nhttp://bayimg.com/CAcGfAaFj&lt;/a&gt; &lt;a href=&quot;\nhttp://bayimg.com/CAcgGAafj&quot; rel=&quot;nofollow&quot; target=&quot;_NEW&quot;&gt;\nhttp://bayimg.com/CAcgGAafj&lt;/a&gt; &lt;a href=&quot;\nhttp://bayimg.com/CACGHaaFj&quot; rel=&quot;nofollow&quot; target=&quot;_NEW&quot;&gt;\nhttp://bayimg.com/CACGHaaFj&lt;/a&gt; &lt;a href=&quot;\nhttp://bayimg.com/CACgIaafJ&quot; rel=&quot;nofollow&quot; target=&quot;_NEW&quot;&gt;\nhttp://bayimg.com/CACgIaafJ&lt;/a&gt; &lt;a href=&quot;\nhttp://bayimg.com/cacGjAAFj&quot; rel=&quot;nofollow&quot; target=&quot;_NEW&quot;&gt;\nhttp://bayimg.com/cacGjAAFj&lt;/a&gt;\n\nAge: 19\nHeight: 5'4&quot;\nWeight: 104lbs\nBust Size: 34B\nHair Color: blond\nModel Number: ali099","torrent":{"xt":"urn:btih:c540e1aeced837e5b225077834e43cbedd0f7214","amp;dn":"ATK+Set+289087+-+Alison+Faye+Gallery+2102013+Toys","amp;tr":["udp%3A%2F%2Ftracker.openbittorrent.com%3A80","udp%3A%2F%2Fopen.demonii.com%3A1337","udp%3A%2F%2Ftracker.coppersurfer.tk%3A6969","udp%3A%2F%2Fexodus.desync.com%3A6969"],"infoHash":"c540e1aeced837e5b225077834e43cbedd0f7214","infoHashBuffer":{"type":"Buffer","data":[197,64,225,174,206,216,55,229,178,37,7,120,52,228,60,190,221,15,114,20]},"announce":[],"urlList":[]}}