{"title":"Chloe Lacourt, Zafira And Billie Star - Out Of Control HD 1080p","uid":9569699,"size":2128234540,"categoryP":"porn","categoryS":"hd___movies","magnet":"?xt=urn:btih:c72e3b2e81cfd8274bb22faf7dcc6769a66705a4&amp;dn=Chloe+Lacourt%2C+Zafira+And+Billie+Star+-+Out+Of+Control+HD+1080p&amp;tr=udp%3A%2F%2Ftracker.openbittorrent.com%3A80&amp;tr=udp%3A%2F%2Fopen.demonii.com%3A1337&amp;tr=udp%3A%2F%2Ftracker.coppersurfer.tk%3A6969&amp;tr=udp%3A%2F%2Fexodus.desync.com%3A6969","seeders":0,"leechers":3,"uploader":"ElitePorn","files":-1,"time":1391561540,"description":"Chloe Lacourt, Zafira And Billie Star - Out Of Control HD 1080p\n---------------------------------------------------------------\n\nScreenshots:\n------------\n\n &lt;a href=&quot;\nhttp://picturescream.asia/soft/RDt&quot; rel=&quot;nofollow&quot; target=&quot;_NEW&quot;&gt;\nhttp://picturescream.asia/soft/RDt&lt;/a&gt;\n &lt;a href=&quot;\nhttp://picturescream.asia/soft/RD2&quot; rel=&quot;nofollow&quot; target=&quot;_NEW&quot;&gt;\nhttp://picturescream.asia/soft/RD2&lt;/a&gt;\n &lt;a href=&quot;\nhttp://picturescream.asia/soft/RDJ&quot; rel=&quot;nofollow&quot; target=&quot;_NEW&quot;&gt;\nhttp://picturescream.asia/soft/RDJ&lt;/a&gt;\n &lt;a href=&quot;\nhttp://picturescream.asia/soft/RDK&quot; rel=&quot;nofollow&quot; target=&quot;_NEW&quot;&gt;\nhttp://picturescream.asia/soft/RDK&lt;/a&gt;\n &lt;a href=&quot;\nhttp://picturescream.asia/soft/RDW&quot; rel=&quot;nofollow&quot; target=&quot;_NEW&quot;&gt;\nhttp://picturescream.asia/soft/RDW&lt;/a&gt;\n &lt;a href=&quot;\nhttp://picturescream.asia/soft/RDf&quot; rel=&quot;nofollow&quot; target=&quot;_NEW&quot;&gt;\nhttp://picturescream.asia/soft/RDf&lt;/a&gt;\n &lt;a href=&quot;\nhttp://picturescream.asia/soft/RDz&quot; rel=&quot;nofollow&quot; target=&quot;_NEW&quot;&gt;\nhttp://picturescream.asia/soft/RDz&lt;/a&gt;\n &lt;a href=&quot;\nhttp://picturescream.asia/soft/RDR&quot; rel=&quot;nofollow&quot; target=&quot;_NEW&quot;&gt;\nhttp://picturescream.asia/soft/RDR&lt;/a&gt;\n\n\nDuration: 34:38, Format: MP4, Resolution: 1920x1080, Size: 1.982 GB","torrent":{"xt":"urn:btih:c72e3b2e81cfd8274bb22faf7dcc6769a66705a4","amp;dn":"Chloe+Lacourt%2C+Zafira+And+Billie+Star+-+Out+Of+Control+HD+1080p","amp;tr":["udp%3A%2F%2Ftracker.openbittorrent.com%3A80","udp%3A%2F%2Fopen.demonii.com%3A1337","udp%3A%2F%2Ftracker.coppersurfer.tk%3A6969","udp%3A%2F%2Fexodus.desync.com%3A6969"],"infoHash":"c72e3b2e81cfd8274bb22faf7dcc6769a66705a4","infoHashBuffer":{"type":"Buffer","data":[199,46,59,46,129,207,216,39,75,178,47,175,125,204,103,105,166,103,5,164]},"announce":[],"urlList":[]}}