{"title":"WWE-ECW.(ECW.Vs.USWA).Civil.War.Of.The.90s.VHSRip.x264-[BWS]","uid":9540813,"size":1643962829,"categoryP":"video","categoryS":"tv_shows","magnet":"?xt=urn:btih:c900741025dc87c2ec4fd3f82420f0fd3381b107&amp;dn=WWE-ECW.%28ECW.Vs.USWA%29.Civil.War.Of.The.90s.VHSRip.x264-%5BBWS%5D&amp;tr=udp%3A%2F%2Ftracker.openbittorrent.com%3A80&amp;tr=udp%3A%2F%2Fopen.demonii.com%3A1337&amp;tr=udp%3A%2F%2Ftracker.coppersurfer.tk%3A6969&amp;tr=udp%3A%2F%2Fexodus.desync.com%3A6969","seeders":0,"leechers":2,"uploader":"mrnow76","files":2,"time":1391038370,"description":"ECW vs. USWA (United Ststes Wrestling Association) Civil War of the 90's \n\nDuration: 90 min\n\n\nThis is a must for all fans of the USWA &amp; ECW. There is nothing more exciting in pro wrestling than a promotion vs promotion feud.\nThey rarely occur in america,but when they do it is very special. Featured are matches,angles,&amp; interviews that aired on both programs.\nThe most exciting angles in years came out of this feud. This starts with jerry lawlers initial challenge to ECW &amp; ends with the \nhardcore heaven 97 showdown between Tommy Dreamer &amp; Jerry Lawler. \n\n1.Jerry Lawler challnges ECW.....USWA\n2.Tommy Dreamer vs Raven..... Jerry Lawlers infamous debut at the ECW Arena....ECW\n3.Fan Cam Intr:Tommy Dreamer....ECW\n4.(2) Interviews :Jerry Lawler....ECW\n5.Tommy Dreamer attacks Jerry Lawler....USWA\n6.Tommy Dreamer-Jerry Lawler ..Confrontation.......USWA\n7.Tommy Dreamer trashes the USWA studio....USWA\n8.Sabu/Rob Van Dam vs Tommy Dreamer/Sandman....Jerry Lawler returns &amp; Jim Cornette debuts...One of the wildest angles ever.....ECW\n9.Intr:Jerry Lawler....ECW\n10.Intr:Beulah ...ECW\n11.Taz burns a WWF t-shirt....ECW\n12.Intr:Jerry Lawler....ECW\n13.Intr:Jim Cornette....ECW\n14.Jerry Lawler/Sabu/Rob Van Dam vs Sandman/Tommy Dreamer/Mystery Partner..SteelCage Match...Rick Rude is the partner &amp; turns on Dreamer &amp; Sandman...One of the most intense matches ever.....ECW\n15.Intr:Jerry Lawler....ECW\n16.Intr:Tommy Dreamer.....ECW\n17.Jerry Lawler burns an ECW t-shirt....USWA\n18.Intr:Tommy Dreamer...USWA\n19.Intr:Sandman...USWA\n20.Intr:Jerry Lawler/Brian Christopher...USWA\n21.Intr:Taz...Clips of Taz are shown...USWA\n22.Intr:Paul Heyman....One of the best interviews ever as Paul is surrounded by ECW guys as he does the interviews &amp; trashes USWA ..Rare and absolutely classic....USWA\n23.Intr:Taz....USWA\n24.Sandman/Tommy Dreamer vs Brian Christopher/Jerry Lawler..Highlights/Total Brawl.....USWA\n25.Intr:Jerry Lawler/Brian Christopher..Lawler get a letter from ECW &amp; addresses the Christopher situation...USWA\n26.Intr:PG-13.....They return alligned with ECW...USWA\n27.Intr:Dutch Mantell....Tommy Dreamer &amp; Jerry Lawler come out &amp; all three brawl all over the studio....USWA\n28.Tommy Dreamer vs Dutch Mantell...Highlights/Beulah &amp; Lawler get involved....USWA\n29.Intr:Jerry Lawler....ECW\n30.Intr:Tommy Dreamer....ECW\n31.Tommy Dreamer vs Jerry Lawler....Hardcore Heaven 97...ECW\n32.Intr:Tommy Dreamer &amp; video","torrent":{"xt":"urn:btih:c900741025dc87c2ec4fd3f82420f0fd3381b107","amp;dn":"WWE-ECW.%28ECW.Vs.USWA%29.Civil.War.Of.The.90s.VHSRip.x264-%5BBWS%5D","amp;tr":["udp%3A%2F%2Ftracker.openbittorrent.com%3A80","udp%3A%2F%2Fopen.demonii.com%3A1337","udp%3A%2F%2Ftracker.coppersurfer.tk%3A6969","udp%3A%2F%2Fexodus.desync.com%3A6969"],"infoHash":"c900741025dc87c2ec4fd3f82420f0fd3381b107","infoHashBuffer":{"type":"Buffer","data":[201,0,116,16,37,220,135,194,236,79,211,248,36,32,240,253,51,129,177,7]},"announce":[],"urlList":[]}}