{"title":"Videoclips","uid":9571465,"size":25467957430,"categoryP":"video","categoryS":"music_videos","magnet":"?xt=urn:btih:c9197672f1ea59f8e1fe83a62a34a703da590437&amp;dn=Videoclips&amp;tr=udp%3A%2F%2Ftracker.openbittorrent.com%3A80&amp;tr=udp%3A%2F%2Fopen.demonii.com%3A1337&amp;tr=udp%3A%2F%2Ftracker.coppersurfer.tk%3A6969&amp;tr=udp%3A%2F%2Fexodus.desync.com%3A6969","seeders":0,"leechers":1,"uploader":"soy_blanco","files":238,"time":1391637525,"description":"238 videoclips de diferentes artistas","torrent":{"xt":"urn:btih:c9197672f1ea59f8e1fe83a62a34a703da590437","amp;dn":"Videoclips","amp;tr":["udp%3A%2F%2Ftracker.openbittorrent.com%3A80","udp%3A%2F%2Fopen.demonii.com%3A1337","udp%3A%2F%2Ftracker.coppersurfer.tk%3A6969","udp%3A%2F%2Fexodus.desync.com%3A6969"],"infoHash":"c9197672f1ea59f8e1fe83a62a34a703da590437","infoHashBuffer":{"type":"Buffer","data":[201,25,118,114,241,234,89,248,225,254,131,166,42,52,167,3,218,89,4,55]},"announce":[],"urlList":[]}}