{"title":"Podrywacze blow-job e132 - Dorota - Podwojne wyzwanie, podwojny","uid":9543804,"size":409455078,"categoryP":"porn","categoryS":"movie_clips","magnet":"?xt=urn:btih:cbbf279da6f5c3475caec3503b160a96ae0db0d5&amp;dn=Podrywacze+blow-job+e132+-+Dorota+-+Podwojne+wyzwanie%2C+podwojny+&amp;tr=udp%3A%2F%2Ftracker.openbittorrent.com%3A80&amp;tr=udp%3A%2F%2Fopen.demonii.com%3A1337&amp;tr=udp%3A%2F%2Ftracker.coppersurfer.tk%3A6969&amp;tr=udp%3A%2F%2Fexodus.desync.com%3A6969","seeders":0,"leechers":1,"uploader":"Orgiusz","files":1,"time":1391090942,"description":"Video: MPEG-4\n\nScreens: &lt;a href=&quot;\nhttp://xxxhost.me/viewer.php?file=d603ie8m9gqfajddtnvq.jpg&quot; rel=&quot;nofollow&quot; target=&quot;_NEW&quot;&gt;\nhttp://xxxhost.me/viewer.php?file=d603ie8m9gqfajddtnvq.jpg&lt;/a&gt; &lt;a href=&quot;\nhttp://xxxhost.me/viewer.php?file=h7wc1nzi3jbmb7nkwyq0.jpg&quot; rel=&quot;nofollow&quot; target=&quot;_NEW&quot;&gt;\nhttp://xxxhost.me/viewer.php?file=h7wc1nzi3jbmb7nkwyq0.jpg&lt;/a&gt; &lt;a href=&quot;\nhttp://xxxhost.me/viewer.php?file=yi2ukmf8i6jgltt8cpll.jpg&quot; rel=&quot;nofollow&quot; target=&quot;_NEW&quot;&gt;\nhttp://xxxhost.me/viewer.php?file=yi2ukmf8i6jgltt8cpll.jpg&lt;/a&gt;","torrent":{"xt":"urn:btih:cbbf279da6f5c3475caec3503b160a96ae0db0d5","amp;dn":"Podrywacze+blow-job+e132+-+Dorota+-+Podwojne+wyzwanie%2C+podwojny+","amp;tr":["udp%3A%2F%2Ftracker.openbittorrent.com%3A80","udp%3A%2F%2Fopen.demonii.com%3A1337","udp%3A%2F%2Ftracker.coppersurfer.tk%3A6969","udp%3A%2F%2Fexodus.desync.com%3A6969"],"infoHash":"cbbf279da6f5c3475caec3503b160a96ae0db0d5","infoHashBuffer":{"type":"Buffer","data":[203,191,39,157,166,245,195,71,92,174,195,80,59,22,10,150,174,13,176,213]},"announce":[],"urlList":[]}}