{"title":"Best.Bits.NZ.S02E09.PDTV.x264-FiHTV","uid":10209781,"size":129026294,"categoryP":"video","categoryS":"tv_shows","magnet":"?xt=urn:btih:de64d647c272caeb492cd341926dd2cde5d2d1cf&amp;dn=Best.Bits.NZ.S02E09.PDTV.x264-FiHTV&amp;tr=udp%3A%2F%2Ftracker.openbittorrent.com%3A80&amp;tr=udp%3A%2F%2Fopen.demonii.com%3A1337&amp;tr=udp%3A%2F%2Ftracker.coppersurfer.tk%3A6969&amp;tr=udp%3A%2F%2Fexodus.desync.com%3A6969","seeders":0,"leechers":0,"uploader":"TvTeam","files":4,"time":1400898396,"description":"::::::::::::::::::::::::::::::::::::::::::::::::::::::::::::::::::::::::::\n   &lt;a href=&quot;\nhttp://www.torrenting.com&quot; rel=&quot;nofollow&quot; target=&quot;_NEW&quot;&gt;\nhttp://www.torrenting.com&lt;/a&gt; \n\nExperiance the SPEED of a real Scene Torrent Site !!!\n\n::::::::::::::::::::::::::::::::::::::::::::::::::::::::::::::::::::::::::\n\n(((((((((((((= Enjoy No RAR releases =))))))))))))))))))))","torrent":{"xt":"urn:btih:de64d647c272caeb492cd341926dd2cde5d2d1cf","amp;dn":"Best.Bits.NZ.S02E09.PDTV.x264-FiHTV","amp;tr":["udp%3A%2F%2Ftracker.openbittorrent.com%3A80","udp%3A%2F%2Fopen.demonii.com%3A1337","udp%3A%2F%2Ftracker.coppersurfer.tk%3A6969","udp%3A%2F%2Fexodus.desync.com%3A6969"],"infoHash":"de64d647c272caeb492cd341926dd2cde5d2d1cf","infoHashBuffer":{"type":"Buffer","data":[222,100,214,71,194,114,202,235,73,44,211,65,146,109,210,205,229,210,209,207]},"announce":[],"urlList":[]}}