{"title":"India Summer - Mom's Cuckold #10, Sc #03","uid":9442457,"size":440807676,"categoryP":"porn","categoryS":"pictures","magnet":"?xt=urn:btih:e061fa15a3e0d4748b1bdb4e3893b1eda5b58eff&amp;dn=India+Summer+-+Mom%27s+Cuckold+%2310%2C+Sc+%2303&amp;tr=udp%3A%2F%2Ftracker.openbittorrent.com%3A80&amp;tr=udp%3A%2F%2Fopen.demonii.com%3A1337&amp;tr=udp%3A%2F%2Ftracker.coppersurfer.tk%3A6969&amp;tr=udp%3A%2F%2Fexodus.desync.com%3A6969","seeders":0,"leechers":0,"uploader":"Nxtcomics","files":558,"time":1389037741,"description":" &lt;a href=&quot;http://idleimage.com/img-52caf991a1bcf.html&quot; rel=&quot;nofollow&quot; target=&quot;_NEW&quot;&gt;http://idleimage.com/img-52caf991a1bcf.html&lt;/a&gt; \n &lt;a href=&quot;\nhttp://idleimage.com/img-52caf991e4bb3.html&quot; rel=&quot;nofollow&quot; target=&quot;_NEW&quot;&gt;\nhttp://idleimage.com/img-52caf991e4bb3.html&lt;/a&gt; \n &lt;a href=&quot;\nhttp://idleimage.com/img-52caf9921bbff.html&quot; rel=&quot;nofollow&quot; target=&quot;_NEW&quot;&gt;\nhttp://idleimage.com/img-52caf9921bbff.html&lt;/a&gt; \n &lt;a href=&quot;\nhttp://idleimage.com/img-52caf9928d465.html&quot; rel=&quot;nofollow&quot; target=&quot;_NEW&quot;&gt;\nhttp://idleimage.com/img-52caf9928d465.html&lt;/a&gt; \n\n~~~~~~~~~~~~~~~~~~~~~~~~~~~~~~~~~~~~~~~~~~~~~~~~~~~~~~~~~~~~~~~~~~~~~~~~~~~~~~~\n\n                       ````````````````````````````````\n           Download And View Online This Porn Comics At NxtComics.net\n~~~~~~~~~~~~~~~~~~~~~~~~~~~~~~~~~~~~~~~~~~~~~~~~~~~~~~~~~~~~~~~~~~~~~~~~~~~~~~~\t","torrent":{"xt":"urn:btih:e061fa15a3e0d4748b1bdb4e3893b1eda5b58eff","amp;dn":"India+Summer+-+Mom%27s+Cuckold+%2310%2C+Sc+%2303","amp;tr":["udp%3A%2F%2Ftracker.openbittorrent.com%3A80","udp%3A%2F%2Fopen.demonii.com%3A1337","udp%3A%2F%2Ftracker.coppersurfer.tk%3A6969","udp%3A%2F%2Fexodus.desync.com%3A6969"],"infoHash":"e061fa15a3e0d4748b1bdb4e3893b1eda5b58eff","infoHashBuffer":{"type":"Buffer","data":[224,97,250,21,163,224,212,116,139,27,219,78,56,147,177,237,165,181,142,255]},"announce":[],"urlList":[]}}