{"title":"Revista Diez Minutos 11.06.14","uid":10291643,"size":18236804,"categoryP":"other","categoryS":"other","magnet":"?xt=urn:btih:e5bad401d09c461be04833087087c51e62f6e6fa&amp;dn=Revista+Diez+Minutos+11.06.14&amp;tr=udp%3A%2F%2Ftracker.openbittorrent.com%3A80&amp;tr=udp%3A%2F%2Fopen.demonii.com%3A1337&amp;tr=udp%3A%2F%2Ftracker.coppersurfer.tk%3A6969&amp;tr=udp%3A%2F%2Fexodus.desync.com%3A6969","seeders":0,"leechers":1,"uploader":"virana","files":1,"time":1401867918,"description":"diez Minutos","torrent":{"xt":"urn:btih:e5bad401d09c461be04833087087c51e62f6e6fa","amp;dn":"Revista+Diez+Minutos+11.06.14","amp;tr":["udp%3A%2F%2Ftracker.openbittorrent.com%3A80","udp%3A%2F%2Fopen.demonii.com%3A1337","udp%3A%2F%2Ftracker.coppersurfer.tk%3A6969","udp%3A%2F%2Fexodus.desync.com%3A6969"],"infoHash":"e5bad401d09c461be04833087087c51e62f6e6fa","infoHashBuffer":{"type":"Buffer","data":[229,186,212,1,208,156,70,27,224,72,51,8,112,135,197,30,98,246,230,250]},"announce":[],"urlList":[]}}