{"title":"Your Mom Tossed My Salad 13 [2014] [DVD-Rip] [XXX]","uid":10179364,"size":2025296110,"categoryP":"porn","categoryS":"movies","magnet":"?xt=urn:btih:f4af5903d1d62e01a0b36ec88afeb79c07e130c4&amp;dn=Your+Mom+Tossed+My+Salad+13+%5B2014%5D+%5BDVD-Rip%5D+%5BXXX%5D&amp;tr=udp%3A%2F%2Ftracker.openbittorrent.com%3A80&amp;tr=udp%3A%2F%2Fopen.demonii.com%3A1337&amp;tr=udp%3A%2F%2Ftracker.coppersurfer.tk%3A6969&amp;tr=udp%3A%2F%2Fexodus.desync.com%3A6969","seeders":0,"leechers":0,"uploader":"makintos13","files":1,"time":1400507431,"description":"Your Mom Tossed My Salad 13 [2014] [DVD-Rip] [XXX]\n\n\nCover:\n &lt;a href=&quot;\nhttp://imgfun.biz/img-5379ef7ec30fc.html&quot; rel=&quot;nofollow&quot; target=&quot;_NEW&quot;&gt;\nhttp://imgfun.biz/img-5379ef7ec30fc.html&lt;/a&gt;\n\n\nCast:\n\n\nAlura Jenson, Holly Heart, Lucky Benton, Mahina Zaltana, Natasha Juja\n\n\nINFO:\n\n\nWatch these cougars attack the butt crack!\n\n\nScreens:\n\n &lt;a href=&quot;\nhttp://imgfun.biz/img-5379efdac89e2.html&quot; rel=&quot;nofollow&quot; target=&quot;_NEW&quot;&gt;\nhttp://imgfun.biz/img-5379efdac89e2.html&lt;/a&gt;\n\n","torrent":{"xt":"urn:btih:f4af5903d1d62e01a0b36ec88afeb79c07e130c4","amp;dn":"Your+Mom+Tossed+My+Salad+13+%5B2014%5D+%5BDVD-Rip%5D+%5BXXX%5D","amp;tr":["udp%3A%2F%2Ftracker.openbittorrent.com%3A80","udp%3A%2F%2Fopen.demonii.com%3A1337","udp%3A%2F%2Ftracker.coppersurfer.tk%3A6969","udp%3A%2F%2Fexodus.desync.com%3A6969"],"infoHash":"f4af5903d1d62e01a0b36ec88afeb79c07e130c4","infoHashBuffer":{"type":"Buffer","data":[244,175,89,3,209,214,46,1,160,179,110,200,138,254,183,156,7,225,48,196]},"announce":[],"urlList":[]}}