{"title":"La France Profonde - Special Gros Calibres","uid":10305901,"size":2337802976,"categoryP":"porn","categoryS":"movies","magnet":"?xt=urn:btih:f59a285da7351822bea135387ce95b97423e1808&amp;dn=La+France+Profonde+-+Special+Gros+Calibres&amp;tr=udp%3A%2F%2Ftracker.openbittorrent.com%3A80&amp;tr=udp%3A%2F%2Fopen.demonii.com%3A1337&amp;tr=udp%3A%2F%2Ftracker.coppersurfer.tk%3A6969&amp;tr=udp%3A%2F%2Fexodus.desync.com%3A6969","seeders":0,"leechers":3,"uploader":"irealu69","files":-1,"time":1402132410,"description":"La France Profonde - Special Gros Calibres\n~~~~~~~~~~~~~~~~~~~~~~~~~~~~~~~~~~~~~~~~~~\n\nScreenshots:\n~~~~~~~~~~~~\n &lt;a href=&quot;\nhttp://picturescream.com/x/clean/fm5G&quot; rel=&quot;nofollow&quot; target=&quot;_NEW&quot;&gt;\nhttp://picturescream.com/x/clean/fm5G&lt;/a&gt;\n &lt;a href=&quot;\nhttp://picturescream.com/x/clean/fm5J&quot; rel=&quot;nofollow&quot; target=&quot;_NEW&quot;&gt;\nhttp://picturescream.com/x/clean/fm5J&lt;/a&gt;\n &lt;a href=&quot;\nhttp://picturescream.com/x/clean/fm5T&quot; rel=&quot;nofollow&quot; target=&quot;_NEW&quot;&gt;\nhttp://picturescream.com/x/clean/fm5T&lt;/a&gt;\n &lt;a href=&quot;\nhttp://picturescream.com/x/clean/fm5x&quot; rel=&quot;nofollow&quot; target=&quot;_NEW&quot;&gt;\nhttp://picturescream.com/x/clean/fm5x&lt;/a&gt;\n &lt;a href=&quot;\nhttp://picturescream.com/x/clean/fm5h&quot; rel=&quot;nofollow&quot; target=&quot;_NEW&quot;&gt;\nhttp://picturescream.com/x/clean/fm5h&lt;/a&gt;\n\n\nVideos Info:\n~~~~~~~~~~~~\nSize: 2.18 GB\nResolution: 704x528","torrent":{"xt":"urn:btih:f59a285da7351822bea135387ce95b97423e1808","amp;dn":"La+France+Profonde+-+Special+Gros+Calibres","amp;tr":["udp%3A%2F%2Ftracker.openbittorrent.com%3A80","udp%3A%2F%2Fopen.demonii.com%3A1337","udp%3A%2F%2Ftracker.coppersurfer.tk%3A6969","udp%3A%2F%2Fexodus.desync.com%3A6969"],"infoHash":"f59a285da7351822bea135387ce95b97423e1808","infoHashBuffer":{"type":"Buffer","data":[245,154,40,93,167,53,24,34,190,161,53,56,124,233,91,151,66,62,24,8]},"announce":[],"urlList":[]}}