{"title":"Wolfgang Amadeus Mozart - 250th Anniversary of Mozart (2006) FLA","uid":10198221,"size":238112944,"categoryP":"audio","categoryS":"flac","magnet":"?xt=urn:btih:f757d0e1f0c073cbbca3ef2d16c4730c10eee69b&amp;dn=Wolfgang+Amadeus+Mozart+-+250th+Anniversary+of+Mozart+%282006%29+FLA&amp;tr=udp%3A%2F%2Ftracker.openbittorrent.com%3A80&amp;tr=udp%3A%2F%2Fopen.demonii.com%3A1337&amp;tr=udp%3A%2F%2Ftracker.coppersurfer.tk%3A6969&amp;tr=udp%3A%2F%2Fexodus.desync.com%3A6969","seeders":0,"leechers":0,"uploader":"Dotexone","files":-1,"time":1400724333,"description":"------------------------------------------------------------\nWolfgang Amadeus Mozart - 250th Anniversary of Mozart (2006)\n------------------------------------------------------------\n\nARTIST: Wolfgang Amadeus Mozart\nALBUM: 250th Anniversary of Mozart - Various Artists - Sinfonia Concertante &amp; Clarinet Concerto\nGENRE: Concerto\nLABEL: KVZ Music\nYEAR: 2006\n\nFORMAT: Free Lossles Audio Codec (FLAC)\nBIT DEPTH: 16 Bits\nSAMPLING RATE: 44.1 KHz\nCHANNEL COUNT: 2 Channels\nMETHOD: Secure | Lossless Level 8 | Accurate","torrent":{"xt":"urn:btih:f757d0e1f0c073cbbca3ef2d16c4730c10eee69b","amp;dn":"Wolfgang+Amadeus+Mozart+-+250th+Anniversary+of+Mozart+%282006%29+FLA","amp;tr":["udp%3A%2F%2Ftracker.openbittorrent.com%3A80","udp%3A%2F%2Fopen.demonii.com%3A1337","udp%3A%2F%2Ftracker.coppersurfer.tk%3A6969","udp%3A%2F%2Fexodus.desync.com%3A6969"],"infoHash":"f757d0e1f0c073cbbca3ef2d16c4730c10eee69b","infoHashBuffer":{"type":"Buffer","data":[247,87,208,225,240,192,115,203,188,163,239,45,22,196,115,12,16,238,230,155]},"announce":[],"urlList":[]}}