{"title":"KarupsHA.14.01.16.Vanessa.Williams.Solo.1.XXX.720p.MP4-KTR","uid":9484204,"size":489416026,"categoryP":"porn","categoryS":"other","magnet":"?xt=urn:btih:f7be2f1ad921a111135761bf08e367b09cb8ede6&amp;dn=KarupsHA.14.01.16.Vanessa.Williams.Solo.1.XXX.720p.MP4-KTR&amp;tr=udp%3A%2F%2Ftracker.openbittorrent.com%3A80&amp;tr=udp%3A%2F%2Fopen.demonii.com%3A1337&amp;tr=udp%3A%2F%2Ftracker.coppersurfer.tk%3A6969&amp;tr=udp%3A%2F%2Fexodus.desync.com%3A6969","seeders":0,"leechers":0,"uploader":"Drarbg","files":4,"time":1389856703,"description":"KarupsHA.14.01.16.Vanessa.Williams.Solo.1.XXX.720p.MP4-KTR\n-----------------------------------------\nScreens : &lt;a href=&quot;\nhttp://imagecurl.org/viewer.php?file=07406711731215252203.jpg&quot; rel=&quot;nofollow&quot; target=&quot;_NEW&quot;&gt;\nhttp://imagecurl.org/viewer.php?file=07406711731215252203.jpg&lt;/a&gt;\n\n","torrent":{"xt":"urn:btih:f7be2f1ad921a111135761bf08e367b09cb8ede6","amp;dn":"KarupsHA.14.01.16.Vanessa.Williams.Solo.1.XXX.720p.MP4-KTR","amp;tr":["udp%3A%2F%2Ftracker.openbittorrent.com%3A80","udp%3A%2F%2Fopen.demonii.com%3A1337","udp%3A%2F%2Ftracker.coppersurfer.tk%3A6969","udp%3A%2F%2Fexodus.desync.com%3A6969"],"infoHash":"f7be2f1ad921a111135761bf08e367b09cb8ede6","infoHashBuffer":{"type":"Buffer","data":[247,190,47,26,217,33,161,17,19,87,97,191,8,227,103,176,156,184,237,230]},"announce":[],"urlList":[]}}