{"title":"Playboy (USA) -{ SEXIEST BABES }- October 2012 - ( May 25, 2014 ","uid":10219055,"size":65497040,"categoryP":"other","categoryS":"e_books","magnet":"?xt=urn:btih:f8a67ec868cff29060cb9a547fb8b1e5c710eb2b&amp;dn=Playboy+%28USA%29+-%7B+SEXIEST+BABES+%7D-+October+2012+-+%28+May+25%2C+2014+&amp;tr=udp%3A%2F%2Ftracker.openbittorrent.com%3A80&amp;tr=udp%3A%2F%2Fopen.demonii.com%3A1337&amp;tr=udp%3A%2F%2Ftracker.coppersurfer.tk%3A6969&amp;tr=udp%3A%2F%2Fexodus.desync.com%3A6969","seeders":0,"leechers":0,"uploader":"KXIP_ET","files":1,"time":1401003690,"description":"COVER :-\n &lt;a href=&quot;\nhttp://s6.postimg.org/ative4oo1/Playboy_Magazine_usa_October_2012.jpg&quot; rel=&quot;nofollow&quot; target=&quot;_NEW&quot;&gt;\nhttp://s6.postimg.org/ative4oo1/Playboy_Magazine_usa_October_2012.jpg&lt;/a&gt;\n\n\n\nInfo :-\n\nLanguage: English\n\nPages: 158\n\nFormat: PDF\n\nSize: 62.46 M.B\n\nCategory: For Men","torrent":{"xt":"urn:btih:f8a67ec868cff29060cb9a547fb8b1e5c710eb2b","amp;dn":"Playboy+%28USA%29+-%7B+SEXIEST+BABES+%7D-+October+2012+-+%28+May+25%2C+2014+","amp;tr":["udp%3A%2F%2Ftracker.openbittorrent.com%3A80","udp%3A%2F%2Fopen.demonii.com%3A1337","udp%3A%2F%2Ftracker.coppersurfer.tk%3A6969","udp%3A%2F%2Fexodus.desync.com%3A6969"],"infoHash":"f8a67ec868cff29060cb9a547fb8b1e5c710eb2b","infoHashBuffer":{"type":"Buffer","data":[248,166,126,200,104,207,242,144,96,203,154,84,127,184,177,229,199,16,235,43]},"announce":[],"urlList":[]}}