{"title":"ATKGalleria.14.05.26.Rose.Red.Masturbation.XXX.1080p.MP4-KTR","uid":10226411,"size":669090415,"categoryP":"porn","categoryS":"other","magnet":"?xt=urn:btih:fcc7f3bc1d37da09b8bba156d86bcd2ff584e817&amp;dn=ATKGalleria.14.05.26.Rose.Red.Masturbation.XXX.1080p.MP4-KTR&amp;tr=udp%3A%2F%2Ftracker.openbittorrent.com%3A80&amp;tr=udp%3A%2F%2Fopen.demonii.com%3A1337&amp;tr=udp%3A%2F%2Ftracker.coppersurfer.tk%3A6969&amp;tr=udp%3A%2F%2Fexodus.desync.com%3A6969","seeders":0,"leechers":1,"uploader":"Drarbg","files":3,"time":1401086967,"description":"ATKGalleria.14.05.26.Rose.Red.Masturbation.XXX.1080p.MP4-KTR\n-----------------------------------------\nScreens : &lt;a href=&quot;\nhttp://imagecurl.org/viewer.php?file=06662451700741798251.jpg&quot; rel=&quot;nofollow&quot; target=&quot;_NEW&quot;&gt;\nhttp://imagecurl.org/viewer.php?file=06662451700741798251.jpg&lt;/a&gt;\n\n","torrent":{"xt":"urn:btih:fcc7f3bc1d37da09b8bba156d86bcd2ff584e817","amp;dn":"ATKGalleria.14.05.26.Rose.Red.Masturbation.XXX.1080p.MP4-KTR","amp;tr":["udp%3A%2F%2Ftracker.openbittorrent.com%3A80","udp%3A%2F%2Fopen.demonii.com%3A1337","udp%3A%2F%2Ftracker.coppersurfer.tk%3A6969","udp%3A%2F%2Fexodus.desync.com%3A6969"],"infoHash":"fcc7f3bc1d37da09b8bba156d86bcd2ff584e817","infoHashBuffer":{"type":"Buffer","data":[252,199,243,188,29,55,218,9,184,187,161,86,216,107,205,47,245,132,232,23]},"announce":[],"urlList":[]}}